{
  "rasa_nlu_data": {
    "regex_features": [],
    "entity_synonyms": [],
    "common_examples": [
      {
        "text": "Vorrei pagare",
        "intent": "paymentRequest",
        "entities": []
      },
      {
        "text": "Vorrei effettuare un pagamento",
        "intent": "paymentRequest",
        "entities": []
      },
      {
        "text": "Paga",
        "intent": "paymentRequest",
        "entities": []
      },
      {
        "text": "Pagare",
        "intent": "paymentRequest",
        "entities": []
      },
      {
        "text": "Vorrei fare una transazione",
        "intent": "paymentRequest",
        "entities": []
      },
      {
        "text": "Vorrei pagare",
        "intent": "paymentRequest",
        "entities": []
      },
      {
        "text": "Voglio pagare qualcuno",
        "intent": "paymentRequest",
        "entities": []
      }
    ]
  }
}
